<archimate:ArchimateDiagramModel
    xmlns:xsi="http://www.w3.org/2001/XMLSchema-instance"
    xmlns:archimate="http://www.archimatetool.com/archimate"
    name="024a Besturen VvE"
    id="id-27cba5270d594d5591a816c9055b5789">
  <children
      xsi:type="archimate:DiagramModelGroup"
      id="id-56078e8270324f5dbc9ec159fdc483e2"
      name="Proces"
      textAlignment="1"
      fillColor="#ffffff"
      documentation="In deze baan staat het bedrijfsproces, de werkprocessen die onderdeel uitmaken van het bedrijfsproces én de gebeurtenissen die de werrkprocessen starten respectievelijk opleveren.">
    <bounds
        x="24"
        y="432"
        width="481"
        height="184"/>
    <children
        xsi:type="archimate:DiagramModelArchimateObject"
        id="id-792675b728b940cb83fef78d06323a44"
        font="1|Segoe UI|11.25|2|WINDOWS|1|-15|0|0|0|400|-1|0|0|0|3|2|1|34|Segoe UI"
        fillColor="#93ccff">
      <sourceConnections
          xsi:type="archimate:DiagramModelArchimateConnection"
          id="id-236c7305a57c443ba97a1bbdf725c00d"
          source="id-792675b728b940cb83fef78d06323a44"
          target="id-c0f976ddbb7d4b7aa57957f8392805ac">
        <bendpoints
            startX="-48"
            startY="-90"
            endX="-48"
            endY="72"/>
        <archimateRelationship
            xsi:type="archimate:RealizationRelationship"
            href="RealizationRelationship_id-1c39b07157164475947a2380b928b9e8.xml#id-1c39b07157164475947a2380b928b9e8"/>
      </sourceConnections>
      <sourceConnections
          xsi:type="archimate:DiagramModelArchimateConnection"
          id="id-b08a5536c58846bb999a473582f17a15"
          source="id-792675b728b940cb83fef78d06323a44"
          target="id-c28d85f191f34d5e89c2dc61c9cd21fd">
        <archimateRelationship
            xsi:type="archimate:AggregationRelationship"
            href="AggregationRelationship_id-04dc7d4b35654ef4979846d2cbb06376.xml#id-04dc7d4b35654ef4979846d2cbb06376"/>
      </sourceConnections>
      <bounds
          x="144"
          y="36"
          width="193"
          height="133"/>
      <children
          xsi:type="archimate:DiagramModelArchimateObject"
          id="id-c28d85f191f34d5e89c2dc61c9cd21fd"
          targetConnections="id-b08a5536c58846bb999a473582f17a15"
          fillColor="#48a8ff"
          textPosition="1">
        <sourceConnections
            xsi:type="archimate:DiagramModelArchimateConnection"
            id="id-54918fcd58054dd2a7919466b80cc305"
            source="id-c28d85f191f34d5e89c2dc61c9cd21fd"
            target="id-c900bd36e84c4a469c723e565750476e">
          <archimateRelationship
              xsi:type="archimate:RealizationRelationship"
              href="RealizationRelationship_id-9137c776a3f040e9af7792cd87d4b7eb.xml#id-9137c776a3f040e9af7792cd87d4b7eb"/>
        </sourceConnections>
        <bounds
            x="36"
            y="48"
            width="120"
            height="55"/>
        <archimateElement
            xsi:type="archimate:BusinessProcess"
            href="BusinessProcess_id-68da2e6798e1475397f591547006c6b1.xml#id-68da2e6798e1475397f591547006c6b1"/>
      </children>
      <archimateElement
          xsi:type="archimate:BusinessProcess"
          href="BusinessProcess_id-3d222da799154fe7942c11b746436544.xml#id-3d222da799154fe7942c11b746436544"/>
    </children>
  </children>
  <children
      xsi:type="archimate:DiagramModelGroup"
      id="id-cc0adef1e2ef4751844961b80b817868"
      name="Resultaat KPI's"
      textAlignment="1"
      fillColor="#ffffff"
      documentation="In deze baan staan de resultaat kPi's">
    <bounds
        x="24"
        y="144"
        width="481"
        height="109"/>
  </children>
  <children
      xsi:type="archimate:DiagramModelGroup"
      id="id-2d07f1e315ff43cb996d9cd1efbdf994"
      name="Risico's"
      textAlignment="1"
      fillColor="#ffffff"
      documentation="In deze baan worden de belangrijkste (bedrijfs/proces)risico's gemodelleerd">
    <bounds
        x="24"
        y="24"
        width="481"
        height="109"/>
  </children>
  <children
      xsi:type="archimate:DiagramModelGroup"
      id="id-41f26bc811324bea9b27be802e6ff52a"
      name="Producten en diensten"
      textAlignment="1"
      fillColor="#ffffff"
      documentation="In deze baan staan de dienst die door het bedrijfsproces wordt gerealiseerd en de bedrijfsservices die door de werkprocessen worden gerealiseerd ">
    <bounds
        x="24"
        y="264"
        width="481"
        height="157"/>
    <children
        xsi:type="archimate:DiagramModelArchimateObject"
        id="id-c0f976ddbb7d4b7aa57957f8392805ac"
        targetConnections="id-236c7305a57c443ba97a1bbdf725c00d"
        fillColor="#fde2cc">
      <sourceConnections
          xsi:type="archimate:DiagramModelArchimateConnection"
          id="id-3b1e3873b6b041ab802a22768f8612f6"
          source="id-c0f976ddbb7d4b7aa57957f8392805ac"
          target="id-c900bd36e84c4a469c723e565750476e">
        <archimateRelationship
            xsi:type="archimate:AggregationRelationship"
            href="AggregationRelationship_id-046a1e99d7924a149bb879ab7aef7518.xml#id-046a1e99d7924a149bb879ab7aef7518"/>
      </sourceConnections>
      <bounds
          x="144"
          y="24"
          width="193"
          height="121"/>
      <children
          xsi:type="archimate:DiagramModelArchimateObject"
          id="id-c900bd36e84c4a469c723e565750476e"
          targetConnections="id-3b1e3873b6b041ab802a22768f8612f6 id-54918fcd58054dd2a7919466b80cc305"
          fillColor="#f9b47b"
          textPosition="1">
        <bounds
            x="24"
            y="36"
            width="145"
            height="55"/>
        <archimateElement
            xsi:type="archimate:BusinessService"
            href="BusinessService_id-094e7a84b3204462a12ea6f8b66ee5b2.xml#id-094e7a84b3204462a12ea6f8b66ee5b2"/>
      </children>
      <archimateElement
          xsi:type="archimate:BusinessService"
          href="BusinessService_id-e5faec46f0ec40c3bebb62e78eef4e98.xml#id-e5faec46f0ec40c3bebb62e78eef4e98"/>
    </children>
  </children>
</archimate:ArchimateDiagramModel>
